aioitertools/__init__.py
aioitertools/asyncio.py
aioitertools/builtins.py
aioitertools/helpers.py
aioitertools/itertools.py
aioitertools/more_itertools.py
aioitertools/py.typed
aioitertools/types.py
aioitertools/tests/__init__.py
aioitertools/tests/__main__.py
aioitertools/tests/asyncio.py
aioitertools/tests/builtins.py
aioitertools/tests/helpers.py
aioitertools/tests/itertools.py
aioitertools/tests/more_itertools.py
aioitertools-0.7.0.dist-info/LICENSE
aioitertools-0.7.0.dist-info/WHEEL
aioitertools-0.7.0.dist-info/METADATA
aioitertools-0.7.0.dist-info/RECORD
