Metadata-Version: 1.1
Name: aioitertools
Version: 0.7.0
Summary: itertools and builtins for AsyncIO and mixed iterables
Home-page: https://aioitertools.omnilib.dev
Author: John Reese
Author-email: john@noswap.com
